kd100/__init__.py
kd100/kd100.py
kd100-0.0.6.dist-info/METADATA
kd100-0.0.6.dist-info/WHEEL
kd100-0.0.6.dist-info/entry_points.txt
kd100-0.0.6.dist-info/top_level.txt
kd100-0.0.6.dist-info/RECORD
