Metadata-Version: 2.1
Name: kd100
Version: 0.0.6
Summary: I'm a small script that help you get express package information use kuaidi100.com api.
Home-page: https://github.com/7sDream/kd100
Author: 7sDream
Author-email: i@7sdre.am
License: MIT
Keywords: internet,query,express,http
Platform: UNKNOWN
Classifier: Development Status :: 3 - Alpha
Classifier: Environment :: Web Environment
Classifier: Intended Audience :: Information Technology
Classifier: Intended Audience :: End Users/Desktop
Classifier: License :: OSI Approved :: MIT License
Classifier: Operating System :: OS Independent
Classifier: Programming Language :: Python
Classifier: Topic :: Internet :: WWW/HTTP
